{
  "version": "0.3.14-fixed",
  "steps": [
    {
      "tag": "CreateModel",
      "model": "Chat"
    },
    {
      "tag": "CreateField",
      "model": "Chat",
      "field": "id",
      "type": "String",
      "arity": "Required"
    },
    {
      "tag": "CreateDirective",
      "location": {
        "path": {
          "tag": "Field",
          "model": "Chat",
          "field": "id"
        },
        "directive": "default"
      }
    },
    {
      "tag": "CreateArgument",
      "location": {
        "tag": "Directive",
        "path": {
          "tag": "Field",
          "model": "Chat",
          "field": "id"
        },
        "directive": "default"
      },
      "argument": "",
      "value": "cuid()"
    },
    {
      "tag": "CreateDirective",
      "location": {
        "path": {
          "tag": "Field",
          "model": "Chat",
          "field": "id"
        },
        "directive": "id"
      }
    },
    {
      "tag": "CreateField",
      "model": "Chat",
      "field": "title",
      "type": "String",
      "arity": "Required"
    },
    {
      "tag": "CreateField",
      "model": "Chat",
      "field": "description",
      "type": "String",
      "arity": "Required"
    }
  ]
}